msnoise/__init__.py
msnoise/_version.py
msnoise/api.py
msnoise/bugreport.py
msnoise/data_structures.py
msnoise/default.py
msnoise/move2obspy.py
msnoise/msnoise_admin.py
msnoise/msnoise_table_def.py
msnoise/preprocessing.py
msnoise/s000installer.py
msnoise/s001configurator.py
msnoise/s002populate_station_table.py
msnoise/s01scan_archive.py
msnoise/s02new_jobs.py
msnoise/s03compute_cc.py
msnoise/s03compute_no_rotation.py
msnoise/s04stack.py
msnoise/s05compute_mwcs.py
msnoise/s06compute_dtt.py
msnoise/s07_compute_dvv.py
msnoise/stretch.py
msnoise/utils.py
msnoise/plots/__init__.py
msnoise/plots/ccftime.py
msnoise/plots/data_availability.py
msnoise/plots/distance.py
msnoise/plots/dtt.py
msnoise/plots/dvv.py
msnoise/plots/interferogram.py
msnoise/plots/mwcs.py
msnoise/plots/spectime.py
msnoise/plots/station_map.py
msnoise/plots/timing.py
msnoise/scripts/__init__.py
msnoise/scripts/msnoise.py
msnoise/static/jquery.min.js
msnoise/static/admin/msnoise.css
msnoise/static/admin/msnoise.png
msnoise/static/admin/style.css
msnoise/templates/index.html
msnoise/templates/admin/about.html
msnoise/templates/admin/bugreport.html
msnoise/templates/admin/data_availability.html
msnoise/templates/admin/index.html
msnoise/templates/admin/interferogram.html
msnoise/templates/admin/master.html
msnoise/templates/admin/results.html
msnoise/templates/admin/model/edit-config.html
msnoise/test/__init__.py
msnoise/test/run_tests.sh
msnoise/test/tests.py
msnoise/test/__pycache__/__init__.cpython-310.pyc
msnoise/test/__pycache__/__init__.cpython-39.pyc
msnoise/test/__pycache__/tests-threecomponent.cpython-310-pytest-8.3.3.pyc
msnoise/test/__pycache__/tests.cpython-310-pytest-8.3.3.pyc
msnoise/test/__pycache__/tests.cpython-310.pyc
msnoise/test/__pycache__/tests.cpython-39.pyc
msnoise/test/data/2010/UV05/HHZ.D/YA.UV05.00.HHZ.D.2010.244
msnoise/test/data/2010/UV06/HHZ.D/YA.UV06.00.HHZ.D.2010.244
msnoise/test/data/2010/UV10/HHZ.D/YA.UV10.00.HHZ.D.2010.244
msnoise-1.6.5.dist-info/licenses/LICENCE.txt
msnoise-1.6.5.dist-info/METADATA
msnoise-1.6.5.dist-info/WHEEL
msnoise-1.6.5.dist-info/entry_points.txt
msnoise-1.6.5.dist-info/top_level.txt
msnoise-1.6.5.dist-info/RECORD
