Metadata-Version: 2.4
Name: msnoise
Version: 1.6.5
Summary: A Python Package for Monitoring Seismic Velocity Changes using Ambient Seismic Noise
Home-page: http://www.msnoise.org
Author: Thomas Lecocq & MSNoise dev team
Author-email: Thomas.Lecocq@seismology.be
License: EUPL-1.1
Keywords: noise monitoring seismic velocity change dvv dtt doublet stretching cross-correlation acoustics seismology
Platform: OS Independent
Classifier: Development Status :: 5 - Production/Stable
Classifier: Environment :: Console
Classifier: Intended Audience :: Science/Research
Classifier: Intended Audience :: Developers
Classifier: Operating System :: OS Independent
Classifier: Programming Language :: Python
Classifier: Programming Language :: Python :: 2
Classifier: Programming Language :: Python :: 2.7
Classifier: Programming Language :: Python :: 3
Classifier: Programming Language :: Python :: 3.7
Classifier: Programming Language :: Python :: 3.8
Classifier: Programming Language :: Python :: 3.9
Classifier: Topic :: Scientific/Engineering
Classifier: Topic :: Scientific/Engineering :: Physics
License-File: LICENCE.txt
Requires-Dist: setuptools
Requires-Dist: numpy>=1.0
Requires-Dist: scipy
Requires-Dist: pandas
Requires-Dist: matplotlib
Requires-Dist: sqlalchemy
Requires-Dist: obspy
Requires-Dist: click
Requires-Dist: pymysql
Requires-Dist: flask
Requires-Dist: flask-admin
Requires-Dist: flask-wtf
Requires-Dist: markdown
Requires-Dist: folium
Requires-Dist: wtforms
Requires-Dist: jinja2
Requires-Dist: scandir
Requires-Dist: logbook
Provides-Extra: doc
Requires-Dist: sphinx>=1.6.1; extra == "doc"
Requires-Dist: sphinx_bootstrap_theme>=0.5.0; extra == "doc"
Requires-Dist: numpydoc; extra == "doc"
Dynamic: author
Dynamic: author-email
Dynamic: classifier
Dynamic: home-page
Dynamic: keywords
Dynamic: license
Dynamic: license-file
Dynamic: platform
Dynamic: provides-extra
Dynamic: requires-dist
Dynamic: summary
